dbl_policy/__init__.py
dbl_policy/allow_all.py
dbl_policy/deny_all.py
dbl_policy/model.py
dbl_policy-0.1.1.dist-info/licenses/LICENSE
dbl_policy-0.1.1.dist-info/METADATA
dbl_policy-0.1.1.dist-info/WHEEL
dbl_policy-0.1.1.dist-info/top_level.txt
dbl_policy-0.1.1.dist-info/RECORD
