Metadata-Version: 2.4
Name: dbl-policy
Version: 0.1.1
Summary: Deterministic policy evaluation layer for dbl-core
Author-email: Lukas Pfister <228201683+lukaspfisterch@users.noreply.github.com>
License: MIT
Project-URL: Repository, https://github.com/lukaspfisterch/dbl-policy
Project-URL: Issues, https://github.com/lukaspfisterch/dbl-policy/issues
Keywords: dbl,policy,governance,deterministic
Classifier: Development Status :: 2 - Pre-Alpha
Classifier: Intended Audience :: Developers
Classifier: License :: OSI Approved :: MIT License
Classifier: Programming Language :: Python :: 3
Classifier: Programming Language :: Python :: 3 :: Only
Classifier: Programming Language :: Python :: 3.11
Classifier: Programming Language :: Python :: 3.12
Classifier: Typing :: Typed
Requires-Python: >=3.11
License-File: LICENSE
Requires-Dist: dbl-core<0.4,>=0.3
Provides-Extra: test
Requires-Dist: pytest<9,>=8; extra == "test"
Provides-Extra: dev
Requires-Dist: pytest<9,>=8; extra == "dev"
Requires-Dist: ruff<1,>=0.5; extra == "dev"
Requires-Dist: mypy<2,>=1.10; extra == "dev"
Dynamic: license-file
